{"YjpcZuBSRgcVQ29akinyuQ==":"img-4561-2000x1500.jpg","InrERnC+bZ9XjfBL7G4bdA==":"mbr-1920x1281.jpg","OCH+aJ7IL7g6swKCi/a7ZA==":"mbr-1920x1280.jpg","6pbCkfTDaL50eKYWtsXeaA==":"mbr-1-1920x1280.jpg","7pfD86rKehj712eBdLQ4YQ==":"img-4488-676x507.jpg","9Bnly17/+AwfOhrFSVygqw==":"img-4561-676x507.jpg","V1Kx8kswMY/Htj3yDhx9ew==":"img-4632-676x507.jpg","iXpB+UIMliwHGt18Bib2Bg==":"img-5365-2000x1500.jpg","dIWSSxDsld1zrZEQCp8dDg==":"_mg-675-1162x775.jpg","ZG5RTA2olWVmGLYI7jrK/g==":"_mg-682-966x644.jpg","w9gNYPko019Ve6F0Foaxxg==":"img-4656-2000x1500.jpg","+KILf/M8zOqCLiwRp2YCUg==":"img-4657-2000x1500.jpg","qK32AQbyBUT87mIeJ5XMSQ==":"img-5865-2000x1500.jpg","v3SPlZj+/MqAq7UsyOnj3g==":"img-5864-2000x1500.jpg","qsV3ZvfBdHXrKuJmt/sTrQ==":"img-5742-2000x1500.jpg","1XrdneZIbRE0FqQVVddtQg==":"img-5741-2000x1500.jpg","9I2AkB41KXk7nSxrdEaW/A==":"img-5740-2000x1500.jpg","DiUtgy9jLnD6s1o6EIQq1A==":"_mg-28-1162x775.jpg","IDJq6t0/5xZQYJ5QZ4GK6g==":"_mg-69-966x644.jpg","b4uuG3Vgb2Zzi88eOIJgdg==":"_mg-28-966x644.jpg","/DrQT9M4qsM+zLtiAn41FA==":"img-5746-1162x872.jpg","QGMHNs6wbIOVG+2Q9dxlAg==":"img-5747-1162x872.jpg","rs+27J3nb9vWFW2zElLATQ==":"img-6333-2000x1500.jpg","Jpard4RKZt7RAC+4HK0mNA==":"received-1915737361831023-1280x960.jpg","YPGKlpOH107Mn8SIwBv25w==":"received-1915737901830969-1280x960.jpg","C8Tgx9dj3fz5h5kG/L7MTg==":"img-6099-2000x1500.jpg","/c0hT/NWNjWGnhZXAfKzhg==":"img-62-2000x1333.jpg","PdYhUupo/U5T3VmwiQbWDg==":"_mg-608-2000x1333.jpg","r5wjulkHycFRVZHEpL5Gtg==":"_mg-104-2000x1333.jpg","DVaRbapdi3TJOdFdqWoOXQ==":"img-122-2000x1333.jpg","A9soDwMCmJgTaVe+6wJriA==":"_mg-720-2000x1333.jpg","YibVHxJYfbtKGIiNgKoBIw==":"img-15-2000x1333.jpg","X7fKJD+z5T15ghzt4oCCXw==":"_mg-454-2000x1333.jpg","C2Mm/Oam0S5zuSxKBBcG9A==":"_mg_0015%20(2)-2000x1333.jpg","xe7Nx83E0f+uUFYXrn5jjw==":"_mg-704-2000x1333.jpg","hjiCoA3CPNQLehBftGJPKg==":"_mg-434-2000x1333.jpg","8u5kkBWj5dVvsCsKZWvl5A==":"img-404-2000x1333.jpg"}